codenerix/__init__.py
codenerix/__init__.pyc
codenerix/apps.py
codenerix/authbackend.py
codenerix/constants.py
codenerix/context.py
codenerix/debug.py
codenerix/debug.pyc
codenerix/decorators.py
codenerix/exceptions.py
codenerix/fields.py
codenerix/forms.py
codenerix/helpers.py
codenerix/middleware.py
codenerix/mixins.py
codenerix/models.py
codenerix/models_people.py
codenerix/multiforms.py
codenerix/py.typed
codenerix/urls.py
codenerix/views.py
codenerix/widgets.py
codenerix/__pycache__/__init__.cpython-310.pyc
codenerix/__pycache__/__init__.cpython-311.pyc
codenerix/__pycache__/__init__.cpython-312.pyc
codenerix/__pycache__/__init__.cpython-313.pyc
codenerix/__pycache__/__init__.cpython-35.pyc
codenerix/__pycache__/__init__.cpython-37.pyc
codenerix/__pycache__/__init__.cpython-38.pyc
codenerix/__pycache__/__init__.cpython-39.pyc
codenerix/__pycache__/apps.cpython-310.pyc
codenerix/__pycache__/apps.cpython-311.pyc
codenerix/__pycache__/apps.cpython-312.pyc
codenerix/__pycache__/apps.cpython-313.pyc
codenerix/__pycache__/apps.cpython-38.pyc
codenerix/__pycache__/apps.cpython-39.pyc
codenerix/__pycache__/authbackend.cpython-310.pyc
codenerix/__pycache__/authbackend.cpython-311.pyc
codenerix/__pycache__/authbackend.cpython-35.pyc
codenerix/__pycache__/authbackend.cpython-38.pyc
codenerix/__pycache__/authbackend.cpython-39.pyc
codenerix/__pycache__/constants.cpython-35.pyc
codenerix/__pycache__/context.cpython-310.pyc
codenerix/__pycache__/context.cpython-311.pyc
codenerix/__pycache__/context.cpython-35.pyc
codenerix/__pycache__/context.cpython-39.pyc
codenerix/__pycache__/debug.cpython-310.pyc
codenerix/__pycache__/debug.cpython-311.pyc
codenerix/__pycache__/debug.cpython-312.pyc
codenerix/__pycache__/debug.cpython-313.pyc
codenerix/__pycache__/debug.cpython-35.pyc
codenerix/__pycache__/debug.cpython-38.pyc
codenerix/__pycache__/debug.cpython-39.pyc
codenerix/__pycache__/decorators.cpython-310.pyc
codenerix/__pycache__/decorators.cpython-311.pyc
django_codenerix-5.0.60.dist-info/LICENSE
django_codenerix-5.0.60.dist-info/METADATA
django_codenerix-5.0.60.dist-info/WHEEL
django_codenerix-5.0.60.dist-info/top_level.txt
django_codenerix-5.0.60.dist-info/RECORD
