Metadata-Version: 2.1
Name: django-codenerix
Version: 5.0.60
Summary: Codenerix it is a framework that goes on top of Django so it makes easier development and building of ERPs.
Home-page: https://github.com/codenerix/django-codenerix
Author: Juanmi Taboada
Author-email: juanmi@juanmitaboada.com
License: Apache License Version 2.0
Keywords: django,codenerix,management,erp,crm
Platform: OS Independent
Classifier: Environment :: Web Environment
Classifier: Framework :: Django
Classifier: Framework :: Django :: 4.0
Classifier: Intended Audience :: Developers
Classifier: License :: Other/Proprietary License
Classifier: Operating System :: OS Independent
Classifier: Programming Language :: Python
Classifier: Programming Language :: Python :: 3
Classifier: Programming Language :: Python :: 3.9
Classifier: Programming Language :: Python :: 3.10
Classifier: Programming Language :: Python :: 3.11
Classifier: Topic :: Internet :: WWW/HTTP
Classifier: Topic :: Internet :: WWW/HTTP :: Dynamic Content
License-File: LICENSE
Requires-Dist: Django >=4.1.1
Requires-Dist: Pillow
Requires-Dist: Unidecode
Requires-Dist: codenerix-lib >=1.0.27
Requires-Dist: django-debug-toolbar-request-history
Requires-Dist: django-debug-toolbar >=4.4.2
Requires-Dist: django-haystack >=2.6.1
Requires-Dist: django-recaptcha <1.3,>=1.2.1
Requires-Dist: django-rosetta >=0.9.8
Requires-Dist: django-stubs
Requires-Dist: django-stubs-ext
Requires-Dist: elasticsearch <3.0.0,>=2.0.0
Requires-Dist: html5lib
Requires-Dist: jsonfield
Requires-Dist: ldap3
Requires-Dist: openpyxl ==3.1.2
Requires-Dist: pyinstrument
Requires-Dist: pymongo
Requires-Dist: pyotp
Requires-Dist: python-dateutil
Requires-Dist: pytz
Requires-Dist: types-pytz
Requires-Dist: yattag
